{"metadata": {"dbt_schema_version": "https://schemas.getdbt.com/dbt/run-results/v4.json", "dbt_version": "1.5.8", "generated_at": "2023-10-24T05:51:50.295748Z", "invocation_id": "8ed12614-fbdf-4e6b-88ea-f38ee73b67c7", "env": {}}, "results": [{"status": "success", "timing": [{"name": "compile", "started_at": "2023-10-24T05:51:07.342505Z", "completed_at": "2023-10-24T05:51:08.262003Z"}, {"name": "execute", "started_at": "2023-10-24T05:51:08.263105Z", "completed_at": "2023-10-24T05:51:08.799103Z"}], "thread_id": "Thread-218", "execution_time": 1.462099313735962, "adapter_response": {"_message": "CREATE VIEW", "code": "CREATE VIEW", "rows_affected": -1}, "message": "CREATE VIEW", "failures": null, "unique_id": "model.tree_aid.stg_beneficiaries_form_data"}, {"status": "success", "timing": [{"name": "compile", "started_at": "2023-10-24T05:51:07.362683Z", "completed_at": "2023-10-24T05:51:07.407050Z"}, {"name": "execute", "started_at": "2023-10-24T05:51:07.408101Z", "completed_at": "2023-10-24T05:51:08.810547Z"}], "thread_id": "Thread-221", "execution_time": 1.4549877643585205, "adapter_response": {"_message": "CREATE VIEW", "code": "CREATE VIEW", "rows_affected": -1}, "message": "CREATE VIEW", "failures": null, "unique_id": "model.tree_aid.stg_survey_definitions_master"}, {"status": "success", "timing": [{"name": "compile", "started_at": "2023-10-24T05:51:07.348677Z", "completed_at": "2023-10-24T05:51:07.495996Z"}, {"name": "execute", "started_at": "2023-10-24T05:51:07.497309Z", "completed_at": "2023-10-24T05:51:08.802027Z"}], "thread_id": "Thread-219", "execution_time": 1.47285795211792, "adapter_response": {"_message": "CREATE VIEW", "code": "CREATE VIEW", "rows_affected": -1}, "message": "CREATE VIEW", "failures": null, "unique_id": "model.tree_aid.stg_core_questions_master"}, {"status": "success", "timing": [{"name": "compile", "started_at": "2023-10-24T05:51:07.357506Z", "completed_at": "2023-10-24T05:51:07.401395Z"}, {"name": "execute", "started_at": "2023-10-24T05:51:07.402573Z", "completed_at": "2023-10-24T05:51:08.864255Z"}], "thread_id": "Thread-220", "execution_time": 1.510873794555664, "adapter_response": {"_message": "SELECT 9690", "code": "SELECT", "rows_affected": 9690}, "message": "SELECT 9690", "failures": null, "unique_id": "model.tree_aid.stg_rhomis_indicators"}, {"status": "success", "timing": [{"name": "compile", "started_at": "2023-10-24T05:51:08.823240Z", "completed_at": "2023-10-24T05:51:08.841111Z"}, {"name": "execute", "started_at": "2023-10-24T05:51:08.842124Z", "completed_at": "2023-10-24T05:51:09.995073Z"}], "thread_id": "Thread-221", "execution_time": 1.1743617057800293, "adapter_response": {"_message": "CREATE VIEW", "code": "CREATE VIEW", "rows_affected": -1}, "message": "CREATE VIEW", "failures": null, "unique_id": "model.tree_aid.stg_beneficiaries"}, {"status": "success", "timing": [{"name": "compile", "started_at": "2023-10-24T05:51:08.807662Z", "completed_at": "2023-10-24T05:51:08.846255Z"}, {"name": "execute", "started_at": "2023-10-24T05:51:08.847357Z", "completed_at": "2023-10-24T05:51:10.114051Z"}], "thread_id": "Thread-218", "execution_time": 1.3090732097625732, "adapter_response": {"_message": "CREATE VIEW", "code": "CREATE VIEW", "rows_affected": -1}, "message": "CREATE VIEW", "failures": null, "unique_id": "model.tree_aid.stg_survey_master"}, {"status": "success", "timing": [{"name": "compile", "started_at": "2023-10-24T05:51:10.120007Z", "completed_at": "2023-10-24T05:51:10.137900Z"}, {"name": "execute", "started_at": "2023-10-24T05:51:10.138922Z", "completed_at": "2023-10-24T05:51:11.307387Z"}], "thread_id": "Thread-221", "execution_time": 1.190018892288208, "adapter_response": {"_message": "CREATE VIEW", "code": "CREATE VIEW", "rows_affected": -1}, "message": "CREATE VIEW", "failures": null, "unique_id": "model.tree_aid.stg_core_questions_union"}, {"status": "success", "timing": [{"name": "compile", "started_at": "2023-10-24T05:51:10.001176Z", "completed_at": "2023-10-24T05:51:10.018899Z"}, {"name": "execute", "started_at": "2023-10-24T05:51:10.019928Z", "completed_at": "2023-10-24T05:51:11.786430Z"}], "thread_id": "Thread-219", "execution_time": 1.788463830947876, "adapter_response": {"_message": "SELECT 170691", "code": "SELECT", "rows_affected": 170691}, "message": "SELECT 170691", "failures": null, "unique_id": "model.tree_aid.beneficiaries"}, {"status": "success", "timing": [{"name": "compile", "started_at": "2023-10-24T05:51:11.313529Z", "completed_at": "2023-10-24T05:51:22.727444Z"}, {"name": "execute", "started_at": "2023-10-24T05:51:22.728570Z", "completed_at": "2023-10-24T05:51:23.442343Z"}], "thread_id": "Thread-218", "execution_time": 12.13136076927185, "adapter_response": {"_message": "SELECT 471", "code": "SELECT", "rows_affected": 471}, "message": "SELECT 471", "failures": null, "unique_id": "model.tree_aid.enterprise_surveys"}, {"status": "success", "timing": [{"name": "compile", "started_at": "2023-10-24T05:51:11.318714Z", "completed_at": "2023-10-24T05:51:28.813281Z"}, {"name": "execute", "started_at": "2023-10-24T05:51:28.814369Z", "completed_at": "2023-10-24T05:51:29.701210Z"}], "thread_id": "Thread-220", "execution_time": 18.384984970092773, "adapter_response": {"_message": "SELECT 1133", "code": "SELECT", "rows_affected": 1133}, "message": "SELECT 1133", "failures": null, "unique_id": "model.tree_aid.land_surveys"}, {"status": "success", "timing": [{"name": "compile", "started_at": "2023-10-24T05:51:29.707059Z", "completed_at": "2023-10-24T05:51:29.726383Z"}, {"name": "execute", "started_at": "2023-10-24T05:51:29.727397Z", "completed_at": "2023-10-24T05:51:30.872246Z"}], "thread_id": "Thread-220", "execution_time": 1.1678686141967773, "adapter_response": {"_message": "CREATE VIEW", "code": "CREATE VIEW", "rows_affected": -1}, "message": "CREATE VIEW", "failures": null, "unique_id": "model.tree_aid.int_land_restoration_activities"}, {"status": "success", "timing": [{"name": "compile", "started_at": "2023-10-24T05:51:23.453259Z", "completed_at": "2023-10-24T05:51:33.014892Z"}, {"name": "execute", "started_at": "2023-10-24T05:51:33.016130Z", "completed_at": "2023-10-24T05:51:34.051492Z"}], "thread_id": "Thread-218", "execution_time": 10.600826740264893, "adapter_response": {"_message": "SELECT 231", "code": "SELECT", "rows_affected": 231}, "message": "SELECT 231", "failures": null, "unique_id": "model.tree_aid.enterprise_survey_product"}, {"status": "success", "timing": [{"name": "compile", "started_at": "2023-10-24T05:51:34.057541Z", "completed_at": "2023-10-24T05:51:34.076043Z"}, {"name": "execute", "started_at": "2023-10-24T05:51:34.077071Z", "completed_at": "2023-10-24T05:51:35.323643Z"}], "thread_id": "Thread-218", "execution_time": 1.2688050270080566, "adapter_response": {"_message": "SELECT 702", "code": "SELECT", "rows_affected": 702}, "message": "SELECT 702", "failures": null, "unique_id": "model.tree_aid.enterprise_survey_product_combined"}, {"status": "success", "timing": [{"name": "compile", "started_at": "2023-10-24T05:51:23.448395Z", "completed_at": "2023-10-24T05:51:37.789843Z"}, {"name": "execute", "started_at": "2023-10-24T05:51:37.790993Z", "completed_at": "2023-10-24T05:51:38.841533Z"}], "thread_id": "Thread-219", "execution_time": 15.395769357681274, "adapter_response": {"_message": "SELECT 75", "code": "SELECT", "rows_affected": 75}, "message": "SELECT 75", "failures": null, "unique_id": "model.tree_aid.enterprise_survey_derivatives"}, {"status": "success", "timing": [{"name": "compile", "started_at": "2023-10-24T05:51:11.352472Z", "completed_at": "2023-10-24T05:51:38.634826Z"}, {"name": "execute", "started_at": "2023-10-24T05:51:38.635914Z", "completed_at": "2023-10-24T05:51:39.540901Z"}], "thread_id": "Thread-221", "execution_time": 28.19114112854004, "adapter_response": {"_message": "CREATE VIEW", "code": "CREATE VIEW", "rows_affected": -1}, "message": "CREATE VIEW", "failures": null, "unique_id": "model.tree_aid.stg_rhomis_data"}, {"status": "success", "timing": [{"name": "compile", "started_at": "2023-10-24T05:51:39.547243Z", "completed_at": "2023-10-24T05:51:39.574544Z"}, {"name": "execute", "started_at": "2023-10-24T05:51:39.575636Z", "completed_at": "2023-10-24T05:51:40.739797Z"}], "thread_id": "Thread-218", "execution_time": 1.1952950954437256, "adapter_response": {"_message": "CREATE VIEW", "code": "CREATE VIEW", "rows_affected": -1}, "message": "CREATE VIEW", "failures": null, "unique_id": "model.tree_aid.rhomis_nrm_techniques"}, {"status": "success", "timing": [{"name": "compile", "started_at": "2023-10-24T05:51:39.552343Z", "completed_at": "2023-10-24T05:51:39.597208Z"}, {"name": "execute", "started_at": "2023-10-24T05:51:39.598215Z", "completed_at": "2023-10-24T05:51:42.048500Z"}], "thread_id": "Thread-219", "execution_time": 2.4989349842071533, "adapter_response": {"_message": "SELECT 11418", "code": "SELECT", "rows_affected": 11418}, "message": "SELECT 11418", "failures": null, "unique_id": "model.tree_aid.rhomis_surveys"}, {"status": "success", "timing": [{"name": "compile", "started_at": "2023-10-24T05:51:40.746148Z", "completed_at": "2023-10-24T05:51:40.764632Z"}, {"name": "execute", "started_at": "2023-10-24T05:51:40.765664Z", "completed_at": "2023-10-24T05:51:42.255348Z"}], "thread_id": "Thread-221", "execution_time": 1.511857509613037, "adapter_response": {"_message": "SELECT 2346", "code": "SELECT", "rows_affected": 2346}, "message": "SELECT 2346", "failures": null, "unique_id": "model.tree_aid.rhomis_nrm_land_techniques"}, {"status": "success", "timing": [{"name": "compile", "started_at": "2023-10-24T05:51:42.058948Z", "completed_at": "2023-10-24T05:51:42.087292Z"}, {"name": "execute", "started_at": "2023-10-24T05:51:42.088352Z", "completed_at": "2023-10-24T05:51:43.302897Z"}], "thread_id": "Thread-218", "execution_time": 1.2467660903930664, "adapter_response": {"_message": "CREATE VIEW", "code": "CREATE VIEW", "rows_affected": -1}, "message": "CREATE VIEW", "failures": null, "unique_id": "model.tree_aid.int_filter_values"}, {"status": "success", "timing": [{"name": "compile", "started_at": "2023-10-24T05:51:42.063179Z", "completed_at": "2023-10-24T05:51:42.159888Z"}, {"name": "execute", "started_at": "2023-10-24T05:51:42.161031Z", "completed_at": "2023-10-24T05:51:43.489836Z"}], "thread_id": "Thread-219", "execution_time": 1.4295594692230225, "adapter_response": {"_message": "SELECT 320", "code": "SELECT", "rows_affected": 320}, "message": "SELECT 320", "failures": null, "unique_id": "model.tree_aid.rhomis_survey_aggregations"}, {"status": "success", "timing": [{"name": "compile", "started_at": "2023-10-24T05:51:42.261479Z", "completed_at": "2023-10-24T05:51:42.278872Z"}, {"name": "execute", "started_at": "2023-10-24T05:51:42.279931Z", "completed_at": "2023-10-24T05:51:43.535829Z"}], "thread_id": "Thread-221", "execution_time": 1.2770795822143555, "adapter_response": {"_message": "SELECT 155", "code": "SELECT", "rows_affected": 155}, "message": "SELECT 155", "failures": null, "unique_id": "model.tree_aid.survey_test"}, {"status": "success", "timing": [{"name": "compile", "started_at": "2023-10-24T05:51:30.877860Z", "completed_at": "2023-10-24T05:51:48.200628Z"}, {"name": "execute", "started_at": "2023-10-24T05:51:48.201752Z", "completed_at": "2023-10-24T05:51:49.452684Z"}], "thread_id": "Thread-220", "execution_time": 18.578062295913696, "adapter_response": {"_message": "SELECT 2566", "code": "SELECT", "rows_affected": 2566}, "message": "SELECT 2566", "failures": null, "unique_id": "model.tree_aid.land_surveys_planted"}], "elapsed_time": 45.90176248550415, "args": {"deprecated_env_var_warnings": [], "log_level": "info", "log_format": "default", "project_dir": "/usr/src/develop/user-115120/environment-212277/repository-159241", "strict_mode": false, "which": "run", "log_file_max_bytes": 10485760, "log_level_file": "debug", "write_json": true, "warn_error_options": {"include": [], "exclude": []}, "populate_cache": true, "log_format_file": "debug", "defer": false, "profiles_dir": "/usr/src/dbt-server-shared/.dbt", "use_colors": true, "quiet": false, "exclude": [], "vars": {}, "partial_parse": true, "static_parser": true, "version_check": true, "send_anonymous_usage_stats": true, "cache_selected_only": false, "log_path": "/usr/src/develop/user-115120/environment-212277/repository-159241/logs", "print": true, "use_colors_file": true, "enable_legacy_logger": true, "favor_state": false, "introspect": true, "select": [], "macro_debugging": false, "printer_width": 80, "indirect_selection": "eager", "rpc_method": "run"}}