{"metadata": {"dbt_schema_version": "https://schemas.getdbt.com/dbt/run-results/v4.json", "dbt_version": "1.5.6", "generated_at": "2023-09-01T10:08:28.089729Z", "invocation_id": "ab015ea3-6648-432c-903f-bbf648067a3d", "env": {}}, "results": [{"status": "success", "timing": [{"name": "compile", "started_at": "2023-09-01T10:07:44.385901Z", "completed_at": "2023-09-01T10:07:44.433339Z"}, {"name": "execute", "started_at": "2023-09-01T10:07:44.434604Z", "completed_at": "2023-09-01T10:07:45.820733Z"}], "thread_id": "Thread-46", "execution_time": 1.437558650970459, "adapter_response": {"_message": "CREATE VIEW", "code": "CREATE VIEW", "rows_affected": -1}, "message": "CREATE VIEW", "failures": null, "unique_id": "model.tree_aid.stg_core_questions_master"}, {"status": "success", "timing": [{"name": "compile", "started_at": "2023-09-01T10:07:44.392062Z", "completed_at": "2023-09-01T10:07:44.491492Z"}, {"name": "execute", "started_at": "2023-09-01T10:07:44.492764Z", "completed_at": "2023-09-01T10:07:45.828880Z"}], "thread_id": "Thread-47", "execution_time": 1.4447557926177979, "adapter_response": {"_message": "SELECT 9690", "code": "SELECT", "rows_affected": 9690}, "message": "SELECT 9690", "failures": null, "unique_id": "model.tree_aid.stg_rhomis_indicators"}, {"status": "success", "timing": [{"name": "compile", "started_at": "2023-09-01T10:07:44.396412Z", "completed_at": "2023-09-01T10:07:44.446368Z"}, {"name": "execute", "started_at": "2023-09-01T10:07:44.447499Z", "completed_at": "2023-09-01T10:07:45.831390Z"}], "thread_id": "Thread-48", "execution_time": 1.442143440246582, "adapter_response": {"_message": "CREATE VIEW", "code": "CREATE VIEW", "rows_affected": -1}, "message": "CREATE VIEW", "failures": null, "unique_id": "model.tree_aid.stg_survey_definitions_master"}, {"status": "success", "timing": [{"name": "compile", "started_at": "2023-09-01T10:07:44.380577Z", "completed_at": "2023-09-01T10:07:45.301525Z"}, {"name": "execute", "started_at": "2023-09-01T10:07:45.302676Z", "completed_at": "2023-09-01T10:07:45.833885Z"}], "thread_id": "Thread-45", "execution_time": 1.4630095958709717, "adapter_response": {"_message": "CREATE VIEW", "code": "CREATE VIEW", "rows_affected": -1}, "message": "CREATE VIEW", "failures": null, "unique_id": "model.tree_aid.stg_beneficiaries_form_data"}, {"status": "success", "timing": [{"name": "compile", "started_at": "2023-09-01T10:07:45.847672Z", "completed_at": "2023-09-01T10:07:45.866291Z"}, {"name": "execute", "started_at": "2023-09-01T10:07:45.867319Z", "completed_at": "2023-09-01T10:07:47.007340Z"}], "thread_id": "Thread-47", "execution_time": 1.1622745990753174, "adapter_response": {"_message": "CREATE VIEW", "code": "CREATE VIEW", "rows_affected": -1}, "message": "CREATE VIEW", "failures": null, "unique_id": "model.tree_aid.stg_beneficiaries"}, {"status": "success", "timing": [{"name": "compile", "started_at": "2023-09-01T10:07:45.826240Z", "completed_at": "2023-09-01T10:07:45.856325Z"}, {"name": "execute", "started_at": "2023-09-01T10:07:45.857325Z", "completed_at": "2023-09-01T10:07:47.106745Z"}], "thread_id": "Thread-46", "execution_time": 1.283198595046997, "adapter_response": {"_message": "CREATE VIEW", "code": "CREATE VIEW", "rows_affected": -1}, "message": "CREATE VIEW", "failures": null, "unique_id": "model.tree_aid.stg_survey_master"}, {"status": "success", "timing": [{"name": "compile", "started_at": "2023-09-01T10:07:47.112892Z", "completed_at": "2023-09-01T10:07:47.129921Z"}, {"name": "execute", "started_at": "2023-09-01T10:07:47.131100Z", "completed_at": "2023-09-01T10:07:48.290126Z"}], "thread_id": "Thread-47", "execution_time": 1.1799733638763428, "adapter_response": {"_message": "CREATE VIEW", "code": "CREATE VIEW", "rows_affected": -1}, "message": "CREATE VIEW", "failures": null, "unique_id": "model.tree_aid.stg_core_questions_union"}, {"status": "success", "timing": [{"name": "compile", "started_at": "2023-09-01T10:07:47.013530Z", "completed_at": "2023-09-01T10:07:47.029469Z"}, {"name": "execute", "started_at": "2023-09-01T10:07:47.030501Z", "completed_at": "2023-09-01T10:07:48.793561Z"}], "thread_id": "Thread-45", "execution_time": 1.7828350067138672, "adapter_response": {"_message": "SELECT 170691", "code": "SELECT", "rows_affected": 170691}, "message": "SELECT 170691", "failures": null, "unique_id": "model.tree_aid.beneficiaries"}, {"status": "success", "timing": [{"name": "compile", "started_at": "2023-09-01T10:07:48.296390Z", "completed_at": "2023-09-01T10:08:00.030501Z"}, {"name": "execute", "started_at": "2023-09-01T10:08:00.031577Z", "completed_at": "2023-09-01T10:08:00.754391Z"}], "thread_id": "Thread-46", "execution_time": 12.460742473602295, "adapter_response": {"_message": "SELECT 471", "code": "SELECT", "rows_affected": 471}, "message": "SELECT 471", "failures": null, "unique_id": "model.tree_aid.enterprise_surveys"}, {"status": "success", "timing": [{"name": "compile", "started_at": "2023-09-01T10:07:48.302014Z", "completed_at": "2023-09-01T10:08:06.074472Z"}, {"name": "execute", "started_at": "2023-09-01T10:08:06.075761Z", "completed_at": "2023-09-01T10:08:06.979180Z"}], "thread_id": "Thread-48", "execution_time": 18.680047035217285, "adapter_response": {"_message": "SELECT 1133", "code": "SELECT", "rows_affected": 1133}, "message": "SELECT 1133", "failures": null, "unique_id": "model.tree_aid.land_surveys"}, {"status": "success", "timing": [{"name": "compile", "started_at": "2023-09-01T10:08:06.985857Z", "completed_at": "2023-09-01T10:08:07.001898Z"}, {"name": "execute", "started_at": "2023-09-01T10:08:07.002961Z", "completed_at": "2023-09-01T10:08:08.148194Z"}], "thread_id": "Thread-48", "execution_time": 1.1655468940734863, "adapter_response": {"_message": "CREATE VIEW", "code": "CREATE VIEW", "rows_affected": -1}, "message": "CREATE VIEW", "failures": null, "unique_id": "model.tree_aid.int_land_restoration_activities"}, {"status": "success", "timing": [{"name": "compile", "started_at": "2023-09-01T10:08:00.765719Z", "completed_at": "2023-09-01T10:08:10.418264Z"}, {"name": "execute", "started_at": "2023-09-01T10:08:10.419615Z", "completed_at": "2023-09-01T10:08:11.474280Z"}], "thread_id": "Thread-46", "execution_time": 10.711503267288208, "adapter_response": {"_message": "SELECT 231", "code": "SELECT", "rows_affected": 231}, "message": "SELECT 231", "failures": null, "unique_id": "model.tree_aid.enterprise_survey_product"}, {"status": "success", "timing": [{"name": "compile", "started_at": "2023-09-01T10:08:11.480867Z", "completed_at": "2023-09-01T10:08:11.498928Z"}, {"name": "execute", "started_at": "2023-09-01T10:08:11.500000Z", "completed_at": "2023-09-01T10:08:12.758049Z"}], "thread_id": "Thread-46", "execution_time": 1.2825772762298584, "adapter_response": {"_message": "SELECT 702", "code": "SELECT", "rows_affected": 702}, "message": "SELECT 702", "failures": null, "unique_id": "model.tree_aid.enterprise_survey_product_combined"}, {"status": "success", "timing": [{"name": "compile", "started_at": "2023-09-01T10:08:00.760672Z", "completed_at": "2023-09-01T10:08:15.294090Z"}, {"name": "execute", "started_at": "2023-09-01T10:08:15.295403Z", "completed_at": "2023-09-01T10:08:16.365766Z"}], "thread_id": "Thread-45", "execution_time": 15.607908725738525, "adapter_response": {"_message": "SELECT 75", "code": "SELECT", "rows_affected": 75}, "message": "SELECT 75", "failures": null, "unique_id": "model.tree_aid.enterprise_survey_derivatives"}, {"status": "success", "timing": [{"name": "compile", "started_at": "2023-09-01T10:07:48.306838Z", "completed_at": "2023-09-01T10:08:15.900749Z"}, {"name": "execute", "started_at": "2023-09-01T10:08:15.902057Z", "completed_at": "2023-09-01T10:08:16.864832Z"}], "thread_id": "Thread-47", "execution_time": 28.560615301132202, "adapter_response": {"_message": "CREATE VIEW", "code": "CREATE VIEW", "rows_affected": -1}, "message": "CREATE VIEW", "failures": null, "unique_id": "model.tree_aid.stg_rhomis_data"}, {"status": "success", "timing": [{"name": "compile", "started_at": "2023-09-01T10:08:16.871018Z", "completed_at": "2023-09-01T10:08:16.897016Z"}, {"name": "execute", "started_at": "2023-09-01T10:08:16.898040Z", "completed_at": "2023-09-01T10:08:18.053922Z"}], "thread_id": "Thread-46", "execution_time": 1.1856775283813477, "adapter_response": {"_message": "CREATE VIEW", "code": "CREATE VIEW", "rows_affected": -1}, "message": "CREATE VIEW", "failures": null, "unique_id": "model.tree_aid.rhomis_nrm_techniques"}, {"status": "success", "timing": [{"name": "compile", "started_at": "2023-09-01T10:08:16.876249Z", "completed_at": "2023-09-01T10:08:16.917544Z"}, {"name": "execute", "started_at": "2023-09-01T10:08:16.918582Z", "completed_at": "2023-09-01T10:08:19.152963Z"}], "thread_id": "Thread-45", "execution_time": 2.2795217037200928, "adapter_response": {"_message": "SELECT 11527", "code": "SELECT", "rows_affected": 11527}, "message": "SELECT 11527", "failures": null, "unique_id": "model.tree_aid.rhomis_surveys"}, {"status": "success", "timing": [{"name": "compile", "started_at": "2023-09-01T10:08:19.159090Z", "completed_at": "2023-09-01T10:08:19.196151Z"}, {"name": "execute", "started_at": "2023-09-01T10:08:19.197151Z", "completed_at": "2023-09-01T10:08:20.341233Z"}], "thread_id": "Thread-47", "execution_time": 1.1848976612091064, "adapter_response": {"_message": "CREATE VIEW", "code": "CREATE VIEW", "rows_affected": -1}, "message": "CREATE VIEW", "failures": null, "unique_id": "model.tree_aid.int_filter_values"}, {"status": "success", "timing": [{"name": "compile", "started_at": "2023-09-01T10:08:19.170606Z", "completed_at": "2023-09-01T10:08:19.191056Z"}, {"name": "execute", "started_at": "2023-09-01T10:08:19.192075Z", "completed_at": "2023-09-01T10:08:20.471319Z"}], "thread_id": "Thread-45", "execution_time": 1.3037190437316895, "adapter_response": {"_message": "SELECT 155", "code": "SELECT", "rows_affected": 155}, "message": "SELECT 155", "failures": null, "unique_id": "model.tree_aid.survey_test"}, {"status": "success", "timing": [{"name": "compile", "started_at": "2023-09-01T10:08:19.164212Z", "completed_at": "2023-09-01T10:08:19.204348Z"}, {"name": "execute", "started_at": "2023-09-01T10:08:19.205347Z", "completed_at": "2023-09-01T10:08:20.491358Z"}], "thread_id": "Thread-46", "execution_time": 1.3296623229980469, "adapter_response": {"_message": "SELECT 256", "code": "SELECT", "rows_affected": 256}, "message": "SELECT 256", "failures": null, "unique_id": "model.tree_aid.rhomis_survey_aggregations"}, {"status": "success", "timing": [{"name": "compile", "started_at": "2023-09-01T10:08:08.154731Z", "completed_at": "2023-09-01T10:08:25.967950Z"}, {"name": "execute", "started_at": "2023-09-01T10:08:25.969169Z", "completed_at": "2023-09-01T10:08:27.246167Z"}], "thread_id": "Thread-48", "execution_time": 19.094533681869507, "adapter_response": {"_message": "SELECT 2566", "code": "SELECT", "rows_affected": 2566}, "message": "SELECT 2566", "failures": null, "unique_id": "model.tree_aid.land_surveys_planted"}], "elapsed_time": 46.704020738601685, "args": {"deprecated_env_var_warnings": [], "send_anonymous_usage_stats": true, "print": true, "log_level_file": "debug", "printer_width": 80, "log_level": "info", "log_file_max_bytes": 10485760, "populate_cache": true, "quiet": false, "enable_legacy_logger": true, "log_format": "default", "cache_selected_only": false, "select": [], "warn_error_options": {"include": [], "exclude": []}, "write_json": true, "log_path": "/usr/src/develop/user-115120/environment-212277/repository-159241/logs", "vars": {}, "defer": false, "indirect_selection": "eager", "project_dir": "/usr/src/develop/user-115120/environment-212277/repository-159241", "use_colors": true, "version_check": true, "profiles_dir": "/usr/src/dbt-server-shared/.dbt", "macro_debugging": false, "partial_parse": true, "strict_mode": false, "use_colors_file": true, "which": "run", "exclude": [], "favor_state": false, "static_parser": true, "log_format_file": "debug", "introspect": true, "rpc_method": "run"}}